soundgen/__init__.py
soundgen/core/sound_down.py
soundgen/core/sound_up.py
soundgen/utils/generate_chirp.py
soundgen/utils/write_wav_file.py
soundgen-1.0.1.dist-info/METADATA
soundgen-1.0.1.dist-info/WHEEL
soundgen-1.0.1.dist-info/RECORD
