Metadata-Version: 2.4
Name: soundgen
Version: 1.0.1
Summary: Library for generating sounds
Project-URL: Homepage, https://github.com/mistertay0dimon/soundgen
Author-email: mistertay0dimn <dimondimonych3@gmail.com>
License-Expression: MIT
Keywords: audio,chirp,generator,sound
Classifier: Development Status :: 5 - Production/Stable
Classifier: Programming Language :: Python :: 3
Classifier: Topic :: Multimedia :: Sound/Audio :: Analysis
Requires-Python: >=3.8
Requires-Dist: numpy>=1.20.0
